llama_index/packs/rag_cli_local/__init__.py
llama_index/packs/rag_cli_local/base.py
llama_index_packs_rag_cli_local-0.4.0.dist-info/METADATA
llama_index_packs_rag_cli_local-0.4.0.dist-info/WHEEL
llama_index_packs_rag_cli_local-0.4.0.dist-info/RECORD
