Metadata-Version: 2.1
Name: llama-index-packs-rag-cli-local
Version: 0.4.0
Summary: llama-index packs rag cli local integration
License: MIT
Keywords: cli,local,rag
Author: Your Name
Author-email: you@example.com
Maintainer: jerryjliu
Requires-Python: >=3.9,<4.0
Classifier: License :: OSI Approved :: MIT License
Classifier: Programming Language :: Python :: 3
Classifier: Programming Language :: Python :: 3.9
Classifier: Programming Language :: Python :: 3.10
Classifier: Programming Language :: Python :: 3.11
Classifier: Programming Language :: Python :: 3.12
Requires-Dist: llama-index-cli (>=0.4.0,<0.5.0)
Requires-Dist: llama-index-core (>=0.12.0,<0.13.0)
Requires-Dist: llama-index-embeddings-huggingface (>=0.4.0,<0.5.0)
Requires-Dist: llama-index-llms-ollama (>=0.4.0,<0.5.0)
Requires-Dist: llama-index-vector-stores-chroma (>=0.4.0,<0.5.0)
